app_min.py
nano_ordinals-0.1.0.dist-info/licenses/LICENSE
nano_ordinals-0.1.0.dist-info/METADATA
nano_ordinals-0.1.0.dist-info/WHEEL
nano_ordinals-0.1.0.dist-info/entry_points.txt
nano_ordinals-0.1.0.dist-info/top_level.txt
nano_ordinals-0.1.0.dist-info/RECORD
