Metadata-Version: 2.4
Name: nano-ordinals
Version: 0.1.0
Summary: Tiny ordinal↔cardinal converter in ~1KB (zero deps)
Author: ozgunlu
License: MIT
Project-URL: Homepage, https://github.com/ozgunlu/nano-ordinals
Project-URL: Issues, https://github.com/ozgunlu/nano-ordinals/issues
Requires-Python: >=3.8
License-File: LICENSE
Dynamic: license-file
